system_info_mcp/__init__.py
system_info_mcp/config.py
system_info_mcp/resources.py
system_info_mcp/server.py
system_info_mcp/tools.py
system_info_mcp/utils.py
mcp_system_info-1.0.1.dist-info/METADATA
mcp_system_info-1.0.1.dist-info/WHEEL
mcp_system_info-1.0.1.dist-info/entry_points.txt
mcp_system_info-1.0.1.dist-info/top_level.txt
mcp_system_info-1.0.1.dist-info/RECORD
