Metadata-Version: 2.4
Name: mcp-system-info
Version: 1.0.1
Summary: System Information MCP Server
Author-email: System Info MCP <noreply@example.com>
Requires-Python: >=3.10
Requires-Dist: mcp>=1.0.0
Requires-Dist: psutil>=5.9.0
Provides-Extra: dev
Requires-Dist: pytest>=7.0.0; extra == "dev"
Requires-Dist: pytest-asyncio>=0.21.0; extra == "dev"
Requires-Dist: black>=23.0.0; extra == "dev"
Requires-Dist: ruff>=0.1.0; extra == "dev"
Requires-Dist: mypy>=1.0.0; extra == "dev"
